{
  "data": {
    "article": {},
    "attachments": {},
    "author_id": "1598557374046179328",
    "conversation_id": "2066223372535820434",
    "created_at": "2026-06-14T20:39:08.000Z",
    "edit_controls": {
      "editable_until": "2026-06-14T21:39:08.000Z",
      "edits_remaining": 5,
      "is_edit_eligible": false
    },
    "edit_history_tweet_ids": [
      "2066259161609089346"
    ],
    "entities": {
      "mentions": [
        {
          "end": 14,
          "id": "2031920545630208000",
          "start": 0,
          "username": "MistLemon2011"
        }
      ]
    },
    "geo": {},
    "id": "2066259161609089346",
    "in_reply_to_user_id": "2031920545630208000",
    "lang": "ja",
    "note_tweet": {
      "entities": {}
    },
    "possibly_sensitive": false,
    "public_metrics": {
      "bookmark_count": 0,
      "impression_count": 0,
      "like_count": 0,
      "quote_count": 0,
      "reply_count": 0,
      "retweet_count": 0
    },
    "referenced_tweets": [
      {
        "id": "2066223372535820434",
        "type": "replied_to"
      }
    ],
    "reply_settings": "everyone",
    "text": "@MistLemon2011 互fo"
  },
  "includes": {
    "tweets": [
      {
        "article": {},
        "attachments": {},
        "author_id": "1598557374046179328",
        "conversation_id": "2066223372535820434",
        "created_at": "2026-06-14T20:39:08.000Z",
        "edit_controls": {
          "editable_until": "2026-06-14T21:39:08.000Z",
          "edits_remaining": 5,
          "is_edit_eligible": false
        },
        "edit_history_tweet_ids": [
          "2066259161609089346"
        ],
        "entities": {
          "mentions": [
            {
              "end": 14,
              "id": "2031920545630208000",
              "start": 0,
              "username": "MistLemon2011"
            }
          ]
        },
        "geo": {},
        "id": "2066259161609089346",
        "in_reply_to_user_id": "2031920545630208000",
        "lang": "ja",
        "note_tweet": {
          "entities": {}
        },
        "possibly_sensitive": false,
        "public_metrics": {
          "bookmark_count": 0,
          "impression_count": 0,
          "like_count": 0,
          "quote_count": 0,
          "reply_count": 0,
          "retweet_count": 0
        },
        "referenced_tweets": [
          {
            "id": "2066223372535820434",
            "type": "replied_to"
          }
        ],
        "reply_settings": "everyone",
        "text": "@MistLemon2011 互fo"
      },
      {
        "article": {},
        "attachments": {},
        "author_id": "2031920545630208000",
        "conversation_id": "2066223372535820434",
        "created_at": "2026-06-14T18:16:55.000Z",
        "edit_controls": {
          "editable_until": "2026-06-14T19:16:55.000Z",
          "edits_remaining": 5,
          "is_edit_eligible": true
        },
        "edit_history_tweet_ids": [
          "2066223372535820434"
        ],
        "entities": {
          "urls": [
            {
              "display_url": "x.com/hakanopesu/sta…",
              "end": 26,
              "expanded_url": "https://twitter.com/hakanopesu/status/2054206543428735427",
              "start": 3,
              "url": "https://t.co/sGl3l1V9pR"
            }
          ]
        },
        "geo": {},
        "id": "2066223372535820434",
        "lang": "ja",
        "note_tweet": {
          "entities": {}
        },
        "possibly_sensitive": false,
        "public_metrics": {
          "bookmark_count": 0,
          "impression_count": 22,
          "like_count": 0,
          "quote_count": 0,
          "reply_count": 1,
          "retweet_count": 0
        },
        "referenced_tweets": [
          {
            "id": "2054206543428735427",
            "type": "quoted"
          }
        ],
        "reply_settings": "everyone",
        "text": "哭了 https://t.co/sGl3l1V9pR"
      }
    ],
    "users": [
      {
        "created_at": "2022-12-02T05:59:21.000Z",
        "derived": {
          "locations": [
            {
              "country_code": "CN",
              "full_name": "Zhuhai, Guangdong Province, China",
              "geo": {
                "coordinates": [
                  113.56778,
                  22.27694
                ],
                "type": "Point"
              },
              "locality": "Zhuhai",
              "region": "Guangdong Province"
            }
          ]
        },
        "description": "|21|心理委员|依存症|mtf|xyn|二次元|特别粘人|不可以欺负我|特别害羞|杂鱼|腹黑|病娇|缺爱|抖M/S|自残|重抑|同类互fo\n\n 主人@Air_Yukiha 妹妹@qiancongxyn 小贱狗 @yuerQwQ",
        "entities": {
          "description": {
            "mentions": [
              {
                "end": 86,
                "start": 75,
                "username": "Air_Yukiha"
              },
              {
                "end": 101,
                "start": 89,
                "username": "qiancongxyn"
              },
              {
                "end": 114,
                "start": 106,
                "username": "yuerQwQ"
              }
            ]
          }
        },
        "id": "1598557374046179328",
        "location": "广州海珠",
        "name": "惠惠🍥🏳️‍⚧️（中二病也要mtf）",
        "profile_image_url": "https://pbs.twimg.com/profile_images/2038850222680633345/r8zG5Gc1_normal.jpg",
        "protected": false,
        "public_metrics": {
          "followers_count": 1482,
          "following_count": 820,
          "like_count": 828,
          "listed_count": 2,
          "media_count": 183,
          "tweet_count": 2015
        },
        "username": "huihui_mikumi",
        "verified": false
      },
      {
        "created_at": "2026-03-12T02:30:48.000Z",
        "description": "2011出厂的次品｜INFP｜公交迷｜中抑轻焦｜MTF｜家长党（？）｜无证含糖｜🍥2026/5/9｜不键政｜无特长无目标无未来的废物｜很想安慰他人奈何我嘴太笨了😢\n恳请包容🥲",
        "id": "2031920545630208000",
        "location": "远在天边",
        "name": "凝矇啊🏳️‍⚧️🍥",
        "profile_image_url": "https://pbs.twimg.com/profile_images/2054920035580403712/OLpB-21o_normal.jpg",
        "protected": false,
        "public_metrics": {
          "followers_count": 315,
          "following_count": 322,
          "like_count": 1788,
          "listed_count": 1,
          "media_count": 11,
          "tweet_count": 229
        },
        "username": "MistLemon2011",
        "verified": false
      }
    ]
  }
}