{
  "data": {
    "article": {},
    "attachments": {},
    "author_id": "1598557374046179328",
    "conversation_id": "2066284376116371789",
    "created_at": "2026-06-14T22:38:20.000Z",
    "edit_controls": {
      "editable_until": "2026-06-14T23:38:20.000Z",
      "edits_remaining": 5,
      "is_edit_eligible": false
    },
    "edit_history_tweet_ids": [
      "2066289160164659309"
    ],
    "entities": {
      "mentions": [
        {
          "end": 16,
          "id": "1488212009787166723",
          "start": 0,
          "username": "Uinxanne_198963"
        },
        {
          "end": 33,
          "id": "1516428117161689091",
          "start": 17,
          "username": "HelpMiaoDestiny"
        },
        {
          "end": 48,
          "id": "1770810702707470336",
          "start": 34,
          "username": "aiheng6499464"
        },
        {
          "end": 64,
          "id": "1545300185169166336",
          "start": 49,
          "username": "JessicaLee9974"
        },
        {
          "end": 72,
          "id": "1379609664938143744",
          "start": 65,
          "username": "JkyDex"
        },
        {
          "end": 89,
          "id": "1861353150386708535",
          "start": 73,
          "username": "KAMOME__KUSHIMA"
        },
        {
          "end": 104,
          "id": "1485662446220201994",
          "start": 90,
          "username": "koinoesutoron"
        },
        {
          "end": 114,
          "id": "1614687093250461696",
          "start": 105,
          "username": "luoyuha9"
        },
        {
          "end": 125,
          "id": "1601549039287566336",
          "start": 115,
          "username": "mmmammm_a"
        },
        {
          "end": 139,
          "id": "1784636606659383296",
          "start": 126,
          "username": "momoya051115"
        },
        {
          "end": 151,
          "id": "1697725634133561344",
          "start": 140,
          "username": "HeXiaoQi77"
        },
        {
          "end": 164,
          "id": "1649365408779214848",
          "start": 152,
          "username": "bolckAshley"
        }
      ]
    },
    "geo": {},
    "id": "2066289160164659309",
    "in_reply_to_user_id": "1488212009787166723",
    "lang": "zh",
    "note_tweet": {
      "entities": {}
    },
    "possibly_sensitive": false,
    "public_metrics": {
      "bookmark_count": 0,
      "impression_count": 0,
      "like_count": 0,
      "quote_count": 0,
      "reply_count": 0,
      "retweet_count": 0
    },
    "referenced_tweets": [
      {
        "id": "2066284376116371789",
        "type": "replied_to"
      }
    ],
    "reply_settings": "everyone",
    "text": "@Uinxanne_198963 @HelpMiaoDestiny @aiheng6499464 @JessicaLee9974 @JkyDex @KAMOME__KUSHIMA @koinoesutoron @luoyuha9 @mmmammm_a @momoya051115 @HeXiaoQi77 @bolckAshley 怎么啦怎么啦"
  },
  "includes": {
    "tweets": [
      {
        "article": {},
        "attachments": {},
        "author_id": "1598557374046179328",
        "conversation_id": "2066284376116371789",
        "created_at": "2026-06-14T22:38:20.000Z",
        "edit_controls": {
          "editable_until": "2026-06-14T23:38:20.000Z",
          "edits_remaining": 5,
          "is_edit_eligible": false
        },
        "edit_history_tweet_ids": [
          "2066289160164659309"
        ],
        "entities": {
          "mentions": [
            {
              "end": 16,
              "id": "1488212009787166723",
              "start": 0,
              "username": "Uinxanne_198963"
            },
            {
              "end": 33,
              "id": "1516428117161689091",
              "start": 17,
              "username": "HelpMiaoDestiny"
            },
            {
              "end": 48,
              "id": "1770810702707470336",
              "start": 34,
              "username": "aiheng6499464"
            },
            {
              "end": 64,
              "id": "1545300185169166336",
              "start": 49,
              "username": "JessicaLee9974"
            },
            {
              "end": 72,
              "id": "1379609664938143744",
              "start": 65,
              "username": "JkyDex"
            },
            {
              "end": 89,
              "id": "1861353150386708535",
              "start": 73,
              "username": "KAMOME__KUSHIMA"
            },
            {
              "end": 104,
              "id": "1485662446220201994",
              "start": 90,
              "username": "koinoesutoron"
            },
            {
              "end": 114,
              "id": "1614687093250461696",
              "start": 105,
              "username": "luoyuha9"
            },
            {
              "end": 125,
              "id": "1601549039287566336",
              "start": 115,
              "username": "mmmammm_a"
            },
            {
              "end": 139,
              "id": "1784636606659383296",
              "start": 126,
              "username": "momoya051115"
            },
            {
              "end": 151,
              "id": "1697725634133561344",
              "start": 140,
              "username": "HeXiaoQi77"
            },
            {
              "end": 164,
              "id": "1649365408779214848",
              "start": 152,
              "username": "bolckAshley"
            }
          ]
        },
        "geo": {},
        "id": "2066289160164659309",
        "in_reply_to_user_id": "1488212009787166723",
        "lang": "zh",
        "note_tweet": {
          "entities": {}
        },
        "possibly_sensitive": false,
        "public_metrics": {
          "bookmark_count": 0,
          "impression_count": 0,
          "like_count": 0,
          "quote_count": 0,
          "reply_count": 0,
          "retweet_count": 0
        },
        "referenced_tweets": [
          {
            "id": "2066284376116371789",
            "type": "replied_to"
          }
        ],
        "reply_settings": "everyone",
        "text": "@Uinxanne_198963 @HelpMiaoDestiny @aiheng6499464 @JessicaLee9974 @JkyDex @KAMOME__KUSHIMA @koinoesutoron @luoyuha9 @mmmammm_a @momoya051115 @HeXiaoQi77 @bolckAshley 怎么啦怎么啦"
      },
      {
        "article": {},
        "attachments": {},
        "author_id": "1488212009787166723",
        "conversation_id": "2066284376116371789",
        "created_at": "2026-06-14T22:19:19.000Z",
        "edit_controls": {
          "editable_until": "2026-06-14T23:19:19.000Z",
          "edits_remaining": 5,
          "is_edit_eligible": true
        },
        "edit_history_tweet_ids": [
          "2066284376116371789"
        ],
        "entities": {
          "mentions": [
            {
              "end": 20,
              "id": "1516428117161689091",
              "start": 4,
              "username": "HelpMiaoDestiny"
            },
            {
              "end": 35,
              "id": "1770810702707470336",
              "start": 21,
              "username": "aiheng6499464"
            },
            {
              "end": 51,
              "id": "1545300185169166336",
              "start": 36,
              "username": "JessicaLee9974"
            },
            {
              "end": 59,
              "id": "1379609664938143744",
              "start": 52,
              "username": "JkyDex"
            },
            {
              "end": 76,
              "id": "1861353150386708535",
              "start": 60,
              "username": "KAMOME__KUSHIMA"
            },
            {
              "end": 91,
              "id": "1485662446220201994",
              "start": 77,
              "username": "koinoesutoron"
            },
            {
              "end": 101,
              "id": "1614687093250461696",
              "start": 92,
              "username": "luoyuha9"
            },
            {
              "end": 112,
              "id": "1601549039287566336",
              "start": 102,
              "username": "mmmammm_a"
            },
            {
              "end": 126,
              "id": "1784636606659383296",
              "start": 113,
              "username": "momoya051115"
            },
            {
              "end": 138,
              "id": "1697725634133561344",
              "start": 127,
              "username": "HeXiaoQi77"
            },
            {
              "end": 151,
              "id": "1649365408779214848",
              "start": 139,
              "username": "bolckAshley"
            },
            {
              "end": 164,
              "id": "1649365408779214848",
              "start": 152,
              "username": "bolckAshley"
            },
            {
              "end": 179,
              "id": "1598557374046179328",
              "start": 165,
              "username": "huihui_mikumi"
            }
          ]
        },
        "geo": {},
        "id": "2066284376116371789",
        "lang": "ja",
        "note_tweet": {
          "entities": {}
        },
        "possibly_sensitive": false,
        "public_metrics": {
          "bookmark_count": 0,
          "impression_count": 9,
          "like_count": 0,
          "quote_count": 0,
          "reply_count": 1,
          "retweet_count": 0
        },
        "reply_settings": "everyone",
        "text": "呼叫隊友@HelpMiaoDestiny @aiheng6499464 @JessicaLee9974 @JkyDex @KAMOME__KUSHIMA @koinoesutoron @luoyuha9 @mmmammm_a @momoya051115 @HeXiaoQi77 @bolckAshley @bolckAshley @huihui_mikumi @Aether9008"
      }
    ],
    "users": [
      {
        "created_at": "2022-12-02T05:59:21.000Z",
        "derived": {
          "locations": [
            {
              "country_code": "CN",
              "full_name": "Zhuhai, Guangdong Province, China",
              "geo": {
                "coordinates": [
                  113.56778,
                  22.27694
                ],
                "type": "Point"
              },
              "locality": "Zhuhai",
              "region": "Guangdong Province"
            }
          ]
        },
        "description": "|21|心理委员|依存症|mtf|xyn|二次元|特别粘人|不可以欺负我|特别害羞|杂鱼|腹黑|病娇|缺爱|抖M/S|自残|重抑|同类互fo\n\n 主人@Air_Yukiha 妹妹@qiancongxyn 小贱狗 @yuerQwQ",
        "entities": {
          "description": {
            "mentions": [
              {
                "end": 86,
                "start": 75,
                "username": "Air_Yukiha"
              },
              {
                "end": 101,
                "start": 89,
                "username": "qiancongxyn"
              },
              {
                "end": 114,
                "start": 106,
                "username": "yuerQwQ"
              }
            ]
          }
        },
        "id": "1598557374046179328",
        "location": "广州海珠",
        "name": "惠惠🍥🏳️‍⚧️（中二病也要mtf）",
        "profile_image_url": "https://pbs.twimg.com/profile_images/2038850222680633345/r8zG5Gc1_normal.jpg",
        "protected": false,
        "public_metrics": {
          "followers_count": 1487,
          "following_count": 820,
          "like_count": 831,
          "listed_count": 2,
          "media_count": 183,
          "tweet_count": 2021
        },
        "username": "huihui_mikumi",
        "verified": false
      },
      {
        "created_at": "2022-01-31T18:06:23.000Z",
        "description": "05♊️/SRS手術慘分享https://t.co/SrMII2t4RC天殘開局|女les/hrt2022.12.20/戰痕纍纍|2024/9家暴轉支持/反Terf/我為自己是藥娘感到自豪",
        "entities": {
          "description": {
            "urls": [
              {
                "display_url": "t.me/zhixinSRSchat/…",
                "end": 36,
                "expanded_url": "https://t.me/zhixinSRSchat/Mtxyn/",
                "start": 13,
                "url": "https://t.co/SrMII2t4RC"
              }
            ]
          }
        },
        "id": "1488212009787166723",
        "location": "藥娘國",
        "name": "温恪姗🏳️‍⚧️⚧️",
        "profile_image_url": "https://pbs.twimg.com/profile_images/1926454952932659200/uOgbYCbL_normal.jpg",
        "protected": false,
        "public_metrics": {
          "followers_count": 490,
          "following_count": 120,
          "like_count": 1544,
          "listed_count": 1,
          "media_count": 105,
          "tweet_count": 1304
        },
        "username": "Uinxanne_198963",
        "verified": false
      },
      {
        "created_at": "2022-04-19T14:48:04.000Z",
        "description": "女大大二/双性恋跨女/童意识19岁雌二醇凝胶猫猫20泰蔡达武变女性术喉结术/废物韭菜/通模难久残废跨女无法骄傲/天赋党母亲党父家暴/脸好看女相女嗓260Hz无伪音/学金融/很穷/绿推/sub小猫/喜欢可爱/求买衣服/民主自由福利/微键政不爆照/167/60/80A/39码/沙漏型/忧郁绝望痛哭树洞/吾将死勿fo",
        "id": "1516428117161689091",
        "location": "深圳～喵～",
        "name": "喵喵～快润🍁或快跳L！",
        "pinned_tweet_id": "1936637694467281234",
        "profile_image_url": "https://pbs.twimg.com/profile_images/1829205405588959236/dsr23eTn_normal.jpg",
        "protected": false,
        "public_metrics": {
          "followers_count": 4868,
          "following_count": 452,
          "like_count": 84240,
          "listed_count": 12,
          "media_count": 1180,
          "tweet_count": 40657
        },
        "username": "HelpMiaoDestiny",
        "verified": false
      },
      {
        "created_at": "2024-03-21T13:52:54.000Z",
        "description": "八年老mtf\n真实的我是个骗子！#双相情感障碍#药娘#易性症联系需门槛费20多了不要请喝杯奶茶不过分吧？多了不要只要20诚心交友不收门槛，以后门槛归为一百",
        "id": "1770810702707470336",
        "location": "江苏省 南京市江宁区谷里街道",
        "name": "千本樱 萌爱🏳️‍⚧️🍥💊",
        "pinned_tweet_id": "1855900792223617052",
        "profile_image_url": "https://pbs.twimg.com/profile_images/2051931727648763904/doRROlo4_normal.jpg",
        "protected": false,
        "public_metrics": {
          "followers_count": 1816,
          "following_count": 888,
          "like_count": 1826,
          "listed_count": 7,
          "media_count": 568,
          "tweet_count": 3552
        },
        "username": "aiheng6499464",
        "verified": false
      },
      {
        "created_at": "2022-07-08T06:54:16.000Z",
        "description": "吃糖9年多的MTF//泰國手術翻譯陪護//PAI診所義務諮詢人員/一星美食獵人//ISTJ-T//",
        "entities": {
          "url": {
            "urls": [
              {
                "display_url": "jessica99.com",
                "end": 23,
                "expanded_url": "https://jessica99.com/",
                "start": 0,
                "url": "https://t.co/hdMsFcDZ0x"
              }
            ]
          }
        },
        "id": "1545300185169166336",
        "location": "Singapore",
        "name": "~嘉嘉~Aka Jessica",
        "pinned_tweet_id": "1785958413970862544",
        "profile_image_url": "https://pbs.twimg.com/profile_images/1731677121901178880/9tf20fwq_normal.jpg",
        "protected": false,
        "public_metrics": {
          "followers_count": 3679,
          "following_count": 154,
          "like_count": 14,
          "listed_count": 14,
          "media_count": 1166,
          "tweet_count": 5638
        },
        "url": "https://t.co/hdMsFcDZ0x",
        "username": "JessicaLee9974",
        "verified": true
      },
      {
        "created_at": "2021-04-07T01:39:59.000Z",
        "description": "非二元 | 23岁 | 含糖🍥 | 行星级三阶 \n贴子成分: 日常/经验/段子/梗图/吵架\n永不投降, 永不放弃. 我们不只是生存, 我们要胜利!\n\n(不常在线, 若想问我问题, 可回帖或私信)",
        "id": "1379609664938143744",
        "location": "银河系-猎户座旋臂",
        "name": "银河仙子🍥",
        "profile_image_url": "https://pbs.twimg.com/profile_images/1841026277396135936/MV3p-LDC_normal.jpg",
        "protected": false,
        "public_metrics": {
          "followers_count": 581,
          "following_count": 68,
          "like_count": 4150,
          "listed_count": 1,
          "media_count": 81,
          "tweet_count": 436
        },
        "username": "JkyDex",
        "verified": true
      },
      {
        "created_at": "2024-11-26T10:16:02.000Z",
        "description": "驅逐馬列黃俄，恢復中華民國！驅逐馬列中共，恢復憲政民主！摧毀中共暴政，光復大陸，還都南京！🇹🇼🇹🇼🇹🇼🇹🇼🇹🇼",
        "id": "1861353150386708535",
        "location": "中華民國 江蘇省",
        "name": "🇹🇼久島鷗🇹🇼",
        "profile_image_url": "https://pbs.twimg.com/profile_images/1861353283262242816/Evp5TxKC_normal.jpg",
        "protected": false,
        "public_metrics": {
          "followers_count": 223,
          "following_count": 673,
          "like_count": 8360,
          "listed_count": 5,
          "media_count": 54,
          "tweet_count": 2605
        },
        "username": "KAMOME__KUSHIMA",
        "verified": false
      },
      {
        "created_at": "2022-01-24T17:15:21.000Z",
        "description": "WikipediaのLTAです。\nLGBT｜ポスドク｜自己嫌悪｜精神疾患｜トランスジェンダー｜LTA｜Wikipedia｜など",
        "entities": {
          "url": {
            "urls": [
              {
                "display_url": "ja.wikipedia.org/wiki/LTA:ISECH…",
                "end": 23,
                "expanded_url": "http://ja.wikipedia.org/wiki/LTA:ISECHIKA",
                "start": 0,
                "url": "https://t.co/Km1SZucwOo"
              }
            ]
          }
        },
        "id": "1485662446220201994",
        "location": "東京 千代田区",
        "name": "伊瀬知夏🏳️‍⚧️",
        "pinned_tweet_id": "1558859092545769472",
        "profile_image_url": "https://pbs.twimg.com/profile_images/1984410811058831363/2uZasvuq_normal.jpg",
        "protected": false,
        "public_metrics": {
          "followers_count": 1291,
          "following_count": 45,
          "like_count": 78,
          "listed_count": 5,
          "media_count": 2740,
          "tweet_count": 9243
        },
        "url": "https://t.co/Km1SZucwOo",
        "username": "koinoesutoron",
        "verified": false
      },
      {
        "created_at": "2023-01-15T18:13:09.000Z",
        "description": "一名普通（transgender）已术跨女（male to female）会发一些日常及有的没的/梦想成为pilot/感谢各位看官打赏/小红书Starla/b站selen空花/热爱旅行、探险、骑行/好友门槛 99 /I have a lot on my shoulders too,so I will not fail",
        "entities": {
          "url": {
            "urls": [
              {
                "display_url": "facebook.com/profile.php?id…",
                "end": 23,
                "expanded_url": "https://www.facebook.com/profile.php?id=61555757532580",
                "start": 0,
                "url": "https://t.co/rbhTCR60nZ"
              }
            ]
          }
        },
        "id": "1614687093250461696",
        "location": "nowhere",
        "name": "Selen（空花）🏳️‍⚧️",
        "pinned_tweet_id": "1952890278395699200",
        "profile_image_url": "https://pbs.twimg.com/profile_images/1676574195361390592/59Zcyz1p_normal.jpg",
        "protected": false,
        "public_metrics": {
          "followers_count": 19321,
          "following_count": 300,
          "like_count": 527,
          "listed_count": 65,
          "media_count": 787,
          "tweet_count": 2016
        },
        "url": "https://t.co/rbhTCR60nZ",
        "username": "luoyuha9",
        "verified": false
      },
      {
        "created_at": "2022-12-10T12:07:11.000Z",
        "description": "🏳️‍🌈🏳️‍⚧️She / They / Transfeminist",
        "id": "1601549039287566336",
        "name": "北雁沐风🏳️‍🌈🏳️‍⚧️",
        "pinned_tweet_id": "2065736948589777357",
        "profile_image_url": "https://pbs.twimg.com/profile_images/1718974847135760384/lV4ZzeQF_normal.jpg",
        "protected": false,
        "public_metrics": {
          "followers_count": 446,
          "following_count": 260,
          "like_count": 9516,
          "listed_count": 2,
          "media_count": 103,
          "tweet_count": 2755
        },
        "username": "mmmammm_a",
        "verified": false
      },
      {
        "created_at": "2024-04-28T17:31:46.000Z",
        "description": "这里是沫沫 2005/11/15  是一个尽力为MTF提供帮助的妹妹",
        "id": "1784636606659383296",
        "location": "沫沫的快乐空间",
        "name": "沫沫酱 winika",
        "pinned_tweet_id": "2016091815460458588",
        "profile_image_url": "https://pbs.twimg.com/profile_images/1807084896474836992/7pHwpbgF_normal.jpg",
        "protected": false,
        "public_metrics": {
          "followers_count": 11783,
          "following_count": 356,
          "like_count": 2071,
          "listed_count": 37,
          "media_count": 430,
          "tweet_count": 3187
        },
        "username": "momoya051115",
        "verified": true
      },
      {
        "created_at": "2023-09-01T21:38:41.000Z",
        "description": "已跨术女，离异带娃。不线下不推广，喜欢干净的Timeline，随机回fo。自用梯子https://t.co/lyPq1p4wfX",
        "entities": {
          "description": {
            "urls": [
              {
                "display_url": "login.doumao.quest/#/register?cod…",
                "end": 64,
                "expanded_url": "https://login.doumao.quest/#/register?code=bo5Qmt30",
                "start": 41,
                "url": "https://t.co/lyPq1p4wfX"
              }
            ]
          },
          "url": {
            "urls": [
              {
                "display_url": "t.me/HeXiaoQi77",
                "end": 23,
                "expanded_url": "https://t.me/HeXiaoQi77",
                "start": 0,
                "url": "https://t.co/r3aQCrk9jR"
              }
            ]
          }
        },
        "id": "1697725634133561344",
        "location": "WIH International Hospital",
        "name": "柒_Rain☕️",
        "pinned_tweet_id": "1913865519406403642",
        "profile_image_url": "https://pbs.twimg.com/profile_images/1862795292178829312/I6s-XESc_normal.jpg",
        "protected": false,
        "public_metrics": {
          "followers_count": 13683,
          "following_count": 288,
          "like_count": 16595,
          "listed_count": 54,
          "media_count": 178,
          "tweet_count": 13462
        },
        "url": "https://t.co/r3aQCrk9jR",
        "username": "HeXiaoQi77",
        "verified": false
      },
      {
        "created_at": "2023-04-21T10:52:19.000Z",
        "description": "When words become empty, silence is power.                𝐒𝐨𝐜𝐢𝐚𝐥 𝐃𝐞𝐦𝐨𝐫𝐚𝐜𝐭🌹𝐚𝐧𝐝 𝐋𝐞𝐟𝐭-𝐓𝐫𝐢𝐝𝐞𝐦𝐢𝐬𝐭❂  ❤️:@Usam8964 好閨蜜:@yuki40582",
        "entities": {
          "description": {
            "mentions": [
              {
                "end": 107,
                "start": 98,
                "username": "Usam8964"
              },
              {
                "end": 122,
                "start": 112,
                "username": "yuki40582"
              }
            ]
          },
          "url": {
            "urls": [
              {
                "display_url": "fes.de",
                "end": 23,
                "expanded_url": "https://www.fes.de",
                "start": 0,
                "url": "https://t.co/7x8MsmOgUP"
              }
            ]
          }
        },
        "id": "1649365408779214848",
        "location": "Fukien, Republic of China",
        "name": "𝐀𝐬𝐡𝐥𝐞𝐲 𝐁𝐥𝐨𝐜𝐤🍥🌹🇹🇼🏳️‍⚧️🇪🇺",
        "pinned_tweet_id": "2031620816308416559",
        "profile_image_url": "https://pbs.twimg.com/profile_images/2045721744514883584/dSGhwjjD_normal.jpg",
        "protected": false,
        "public_metrics": {
          "followers_count": 3608,
          "following_count": 2084,
          "like_count": 42065,
          "listed_count": 31,
          "media_count": 1665,
          "tweet_count": 22548
        },
        "url": "https://t.co/7x8MsmOgUP",
        "username": "bolckAshley",
        "verified": true
      }
    ]
  }
}