{
  "data": {
    "article": {},
    "attachments": {},
    "author_id": "1598557374046179328",
    "conversation_id": "2061714067031781840",
    "created_at": "2026-06-02T19:13:00.000Z",
    "edit_controls": {
      "editable_until": "2026-06-02T20:13:00.000Z",
      "edits_remaining": 5,
      "is_edit_eligible": false
    },
    "edit_history_tweet_ids": [
      "2061888835085369668"
    ],
    "entities": {
      "mentions": [
        {
          "end": 9,
          "id": "1452537509875834880",
          "start": 0,
          "username": "kkggxxyy"
        }
      ]
    },
    "geo": {},
    "id": "2061888835085369668",
    "in_reply_to_user_id": "1452537509875834880",
    "lang": "ja",
    "note_tweet": {
      "entities": {}
    },
    "possibly_sensitive": false,
    "public_metrics": {
      "bookmark_count": 0,
      "impression_count": 0,
      "like_count": 0,
      "quote_count": 0,
      "reply_count": 0,
      "retweet_count": 0
    },
    "referenced_tweets": [
      {
        "id": "2061714067031781840",
        "type": "replied_to"
      }
    ],
    "reply_settings": "everyone",
    "text": "@kkggxxyy жҒӯе–ңжҚҸ"
  },
  "includes": {
    "media": [
      {
        "height": 2048,
        "media_key": "3_2061714061373722624",
        "public_metrics": {},
        "type": "photo",
        "url": "https://pbs.twimg.com/media/HJyuA_Cb0AAxGvk.jpg",
        "width": 1611
      }
    ],
    "tweets": [
      {
        "article": {},
        "attachments": {},
        "author_id": "1598557374046179328",
        "conversation_id": "2061714067031781840",
        "created_at": "2026-06-02T19:13:00.000Z",
        "edit_controls": {
          "editable_until": "2026-06-02T20:13:00.000Z",
          "edits_remaining": 5,
          "is_edit_eligible": false
        },
        "edit_history_tweet_ids": [
          "2061888835085369668"
        ],
        "entities": {
          "mentions": [
            {
              "end": 9,
              "id": "1452537509875834880",
              "start": 0,
              "username": "kkggxxyy"
            }
          ]
        },
        "geo": {},
        "id": "2061888835085369668",
        "in_reply_to_user_id": "1452537509875834880",
        "lang": "ja",
        "note_tweet": {
          "entities": {}
        },
        "possibly_sensitive": false,
        "public_metrics": {
          "bookmark_count": 0,
          "impression_count": 0,
          "like_count": 0,
          "quote_count": 0,
          "reply_count": 0,
          "retweet_count": 0
        },
        "referenced_tweets": [
          {
            "id": "2061714067031781840",
            "type": "replied_to"
          }
        ],
        "reply_settings": "everyone",
        "text": "@kkggxxyy жҒӯе–ңжҚҸ"
      },
      {
        "article": {},
        "attachments": {
          "media_keys": [
            "3_2061714061373722624"
          ]
        },
        "author_id": "1452537509875834880",
        "conversation_id": "2061714067031781840",
        "created_at": "2026-06-02T07:38:33.000Z",
        "edit_controls": {
          "editable_until": "2026-06-02T08:38:33.000Z",
          "edits_remaining": 5,
          "is_edit_eligible": true
        },
        "edit_history_tweet_ids": [
          "2061714067031781840"
        ],
        "entities": {
          "urls": [
            {
              "display_url": "pic.x.com/OuD6QPwec7",
              "end": 37,
              "expanded_url": "https://x.com/kkggxxyy/status/2061714067031781840/photo/1",
              "media_key": "3_2061714061373722624",
              "start": 14,
              "url": "https://t.co/OuD6QPwec7"
            }
          ]
        },
        "geo": {},
        "id": "2061714067031781840",
        "lang": "zh",
        "note_tweet": {
          "entities": {}
        },
        "possibly_sensitive": false,
        "public_metrics": {
          "bookmark_count": 1,
          "impression_count": 2859,
          "like_count": 54,
          "quote_count": 0,
          "reply_count": 21,
          "retweet_count": 0
        },
        "reply_settings": "everyone",
        "text": "еҺҶж—¶дёүе‘ЁиҠұиҙ№40дёҮжӢҝдёӢеӨ§иҜҒ https://t.co/OuD6QPwec7"
      }
    ],
    "users": [
      {
        "created_at": "2022-12-02T05:59:21.000Z",
        "description": "|21|еҝғзҗҶе§”е‘ҳ|дҫқеӯҳз—Ү|mtf|xyn|дәҢж¬Ўе…ғ|зү№еҲ«зІҳдәә|дёҚеҸҜд»Ҙж¬әиҙҹжҲ‘|зү№еҲ«е®ізҫһ|жқӮйұј|и…№й»‘|з—…еЁҮ|зјәзҲұ|жҠ–M/S|иҮӘж®Ӣ|йҮҚжҠ‘|еҗҢзұ»дә’fo",
        "id": "1598557374046179328",
        "location": "е№ҝе·һжө·зҸ ",
        "name": "жғ жғ рҹҚҘрҹҸіпёҸвҖҚвҡ§пёҸпјҲдёӯдәҢз—…д№ҹиҰҒmtfпјү",
        "profile_image_url": "https://pbs.twimg.com/profile_images/2038850222680633345/r8zG5Gc1_normal.jpg",
        "protected": false,
        "public_metrics": {
          "followers_count": 1103,
          "following_count": 594,
          "like_count": 625,
          "listed_count": 1,
          "media_count": 152,
          "tweet_count": 1373
        },
        "username": "huihui_mikumi",
        "verified": false
      },
      {
        "created_at": "2021-10-25T07:28:33.000Z",
        "description": "рҹҸіпёҸвҖҚвҡ§пёҸ дёҚеҸҜз»“зјҳ",
        "id": "1452537509875834880",
        "location": "еӨ§иұЎйј»еӯҗ",
        "name": "н•ҳлӮҳлӮҳ",
        "profile_image_url": "https://pbs.twimg.com/profile_images/2043310679210569728/ph6qicjz_normal.jpg",
        "protected": false,
        "public_metrics": {
          "followers_count": 703,
          "following_count": 242,
          "like_count": 7028,
          "listed_count": 0,
          "media_count": 244,
          "tweet_count": 6274
        },
        "username": "kkggxxyy",
        "verified": true
      }
    ]
  }
}