{
  "data": {
    "article": {},
    "attachments": {},
    "author_id": "1598557374046179328",
    "conversation_id": "2055937285166968889",
    "created_at": "2026-05-17T10:46:58.000Z",
    "edit_controls": {
      "editable_until": "2026-05-17T11:46:58.000Z",
      "edits_remaining": 5,
      "is_edit_eligible": false
    },
    "edit_history_tweet_ids": [
      "2055963278149664920"
    ],
    "entities": {
      "mentions": [
        {
          "end": 7,
          "id": "1831350388861345793",
          "start": 0,
          "username": "Hiime0"
        }
      ]
    },
    "geo": {},
    "id": "2055963278149664920",
    "in_reply_to_user_id": "1831350388861345793",
    "lang": "zh",
    "note_tweet": {
      "entities": {}
    },
    "possibly_sensitive": false,
    "public_metrics": {
      "bookmark_count": 0,
      "impression_count": 0,
      "like_count": 0,
      "quote_count": 0,
      "reply_count": 0,
      "retweet_count": 0
    },
    "referenced_tweets": [
      {
        "id": "2055963189414875470",
        "type": "replied_to"
      }
    ],
    "reply_settings": "everyone",
    "text": "@Hiime0 广州塔底下"
  },
  "includes": {
    "tweets": [
      {
        "article": {},
        "attachments": {},
        "author_id": "1598557374046179328",
        "conversation_id": "2055937285166968889",
        "created_at": "2026-05-17T10:46:58.000Z",
        "edit_controls": {
          "editable_until": "2026-05-17T11:46:58.000Z",
          "edits_remaining": 5,
          "is_edit_eligible": false
        },
        "edit_history_tweet_ids": [
          "2055963278149664920"
        ],
        "entities": {
          "mentions": [
            {
              "end": 7,
              "id": "1831350388861345793",
              "start": 0,
              "username": "Hiime0"
            }
          ]
        },
        "geo": {},
        "id": "2055963278149664920",
        "in_reply_to_user_id": "1831350388861345793",
        "lang": "zh",
        "note_tweet": {
          "entities": {}
        },
        "possibly_sensitive": false,
        "public_metrics": {
          "bookmark_count": 0,
          "impression_count": 0,
          "like_count": 0,
          "quote_count": 0,
          "reply_count": 0,
          "retweet_count": 0
        },
        "referenced_tweets": [
          {
            "id": "2055963189414875470",
            "type": "replied_to"
          }
        ],
        "reply_settings": "everyone",
        "text": "@Hiime0 广州塔底下"
      },
      {
        "article": {},
        "attachments": {},
        "author_id": "1831350388861345793",
        "conversation_id": "2055937285166968889",
        "created_at": "2026-05-17T10:46:36.000Z",
        "edit_controls": {
          "editable_until": "2026-05-17T11:46:36.000Z",
          "edits_remaining": 5,
          "is_edit_eligible": false
        },
        "edit_history_tweet_ids": [
          "2055963189414875470"
        ],
        "entities": {
          "mentions": [
            {
              "end": 14,
              "id": "1598557374046179328",
              "start": 0,
              "username": "huihui_mikumi"
            }
          ]
        },
        "geo": {},
        "id": "2055963189414875470",
        "in_reply_to_user_id": "1598557374046179328",
        "lang": "en",
        "note_tweet": {
          "entities": {}
        },
        "possibly_sensitive": false,
        "public_metrics": {
          "bookmark_count": 0,
          "impression_count": 2,
          "like_count": 0,
          "quote_count": 0,
          "reply_count": 1,
          "retweet_count": 0
        },
        "referenced_tweets": [
          {
            "id": "2055937285166968889",
            "type": "replied_to"
          }
        ],
        "reply_settings": "everyone",
        "text": "@huihui_mikumi where"
      }
    ],
    "users": [
      {
        "created_at": "2022-12-02T05:59:21.000Z",
        "derived": {
          "locations": [
            {
              "country_code": "CN",
              "full_name": "Zhuhai, Guangdong Province, China",
              "geo": {
                "coordinates": [
                  113.56778,
                  22.27694
                ],
                "type": "Point"
              },
              "locality": "Zhuhai",
              "region": "Guangdong Province"
            }
          ]
        },
        "description": "|21|心理委员|依存症|mtf|xyn|二次元|特别粘人|不可以欺负我|特别害羞|杂鱼|腹黑|病娇|缺爱|抖M/S|自残|重抑|同类互fo",
        "id": "1598557374046179328",
        "location": "广州海珠",
        "name": "惠惠🍥🏳️‍⚧️（中二病也要mtf）",
        "pinned_tweet_id": "2039216871254401419",
        "profile_image_url": "https://pbs.twimg.com/profile_images/2038850222680633345/r8zG5Gc1_normal.jpg",
        "protected": false,
        "public_metrics": {
          "followers_count": 931,
          "following_count": 502,
          "like_count": 522,
          "listed_count": 1,
          "media_count": 133,
          "tweet_count": 1109
        },
        "username": "huihui_mikumi",
        "verified": false
      },
      {
        "created_at": "2024-09-04T15:15:42.000Z",
        "description": "黑色的荆棘扼住她的咽喉，永恒的夜消融了她的心脏。沉溺在“等待”中的她呀，总有一天，白霜般的月光会洒满你遍体鳞伤的娇躯，把你变成殿堂上转着裙摆的女孩。\n【详情见置顶帖】",
        "entities": {
          "url": {
            "urls": [
              {
                "display_url": "t.me/Hiime0",
                "end": 23,
                "expanded_url": "http://t.me/Hiime0",
                "start": 0,
                "url": "https://t.co/nKdFGtLRKc"
              }
            ]
          }
        },
        "id": "1831350388861345793",
        "location": "上海",
        "name": "𝐻𝑖𝑖𝑚𝑒🍡🍥",
        "pinned_tweet_id": "2055602008976199849",
        "profile_image_url": "https://pbs.twimg.com/profile_images/2054384234526388224/MagCt1ZF_normal.jpg",
        "protected": false,
        "public_metrics": {
          "followers_count": 629,
          "following_count": 240,
          "like_count": 564,
          "listed_count": 2,
          "media_count": 151,
          "tweet_count": 747
        },
        "url": "https://t.co/nKdFGtLRKc",
        "username": "Hiime0",
        "verified": true
      }
    ]
  }
}