{
  "data": {
    "article": {},
    "attachments": {},
    "author_id": "1598557374046179328",
    "conversation_id": "2038341423808835885",
    "created_at": "2026-03-30T10:31:10.000Z",
    "edit_controls": {
      "editable_until": "2026-03-30T11:31:10.000Z",
      "edits_remaining": 5,
      "is_edit_eligible": false
    },
    "edit_history_tweet_ids": [
      "2038564684476133567"
    ],
    "entities": {
      "mentions": [
        {
          "end": 16,
          "id": "1608743804034756609",
          "start": 0,
          "username": "catcatnekoyayay"
        }
      ]
    },
    "geo": {},
    "id": "2038564684476133567",
    "in_reply_to_user_id": "1608743804034756609",
    "lang": "ja",
    "note_tweet": {
      "entities": {}
    },
    "possibly_sensitive": false,
    "public_metrics": {
      "bookmark_count": 0,
      "impression_count": 0,
      "like_count": 0,
      "quote_count": 0,
      "reply_count": 0,
      "retweet_count": 0
    },
    "referenced_tweets": [
      {
        "id": "2038341423808835885",
        "type": "replied_to"
      }
    ],
    "reply_settings": "everyone",
    "text": "@catcatnekoyayay 抱抱小眠"
  },
  "includes": {
    "tweets": [
      {
        "article": {},
        "attachments": {},
        "author_id": "1598557374046179328",
        "conversation_id": "2038341423808835885",
        "created_at": "2026-03-30T10:31:10.000Z",
        "edit_controls": {
          "editable_until": "2026-03-30T11:31:10.000Z",
          "edits_remaining": 5,
          "is_edit_eligible": false
        },
        "edit_history_tweet_ids": [
          "2038564684476133567"
        ],
        "entities": {
          "mentions": [
            {
              "end": 16,
              "id": "1608743804034756609",
              "start": 0,
              "username": "catcatnekoyayay"
            }
          ]
        },
        "geo": {},
        "id": "2038564684476133567",
        "in_reply_to_user_id": "1608743804034756609",
        "lang": "ja",
        "note_tweet": {
          "entities": {}
        },
        "possibly_sensitive": false,
        "public_metrics": {
          "bookmark_count": 0,
          "impression_count": 0,
          "like_count": 0,
          "quote_count": 0,
          "reply_count": 0,
          "retweet_count": 0
        },
        "referenced_tweets": [
          {
            "id": "2038341423808835885",
            "type": "replied_to"
          }
        ],
        "reply_settings": "everyone",
        "text": "@catcatnekoyayay 抱抱小眠"
      },
      {
        "article": {},
        "attachments": {},
        "author_id": "1608743804034756609",
        "conversation_id": "2038341423808835885",
        "created_at": "2026-03-29T19:44:00.000Z",
        "edit_controls": {
          "editable_until": "2026-03-29T20:44:00.000Z",
          "edits_remaining": 5,
          "is_edit_eligible": true
        },
        "edit_history_tweet_ids": [
          "2038341423808835885"
        ],
        "entities": {},
        "geo": {},
        "id": "2038341423808835885",
        "lang": "zh",
        "note_tweet": {
          "entities": {}
        },
        "possibly_sensitive": false,
        "public_metrics": {
          "bookmark_count": 0,
          "impression_count": 42,
          "like_count": 1,
          "quote_count": 0,
          "reply_count": 2,
          "retweet_count": 0
        },
        "reply_settings": "everyone",
        "text": "我真的不想上学了呃呃……我会死的"
      }
    ],
    "users": [
      {
        "created_at": "2022-12-02T05:59:21.000Z",
        "derived": {
          "locations": [
            {
              "country_code": "CN",
              "full_name": "Guangzhou, Guangdong Province, China",
              "geo": {
                "coordinates": [
                  113.25,
                  23.11667
                ],
                "type": "Point"
              },
              "locality": "Guangzhou",
              "region": "Guangdong Province"
            }
          ]
        },
        "description": "|21|心理委员|依存症|mtf|xyn|二次元|特别粘人|不可以欺负我|特别害羞|杂鱼\n|腹黑|病娇|OD药|缺爱|抖M/S|自残|随缘fo\n\n在替某人活下去，帮助更多想结束生命之人",
        "id": "1598557374046179328",
        "location": "广州",
        "name": "惠惠🍥🏳️‍⚧️（中二病也要mtf）",
        "profile_image_url": "https://pbs.twimg.com/profile_images/2033641073965469699/6fcuj7zj_normal.jpg",
        "protected": false,
        "public_metrics": {
          "followers_count": 49,
          "following_count": 73,
          "like_count": 102,
          "listed_count": 0,
          "media_count": 42,
          "tweet_count": 183
        },
        "username": "huihui_mikumi",
        "verified": false
      },
      {
        "created_at": "2022-12-30T08:36:33.000Z",
        "description": "❄️直接叫我眠眠or咩咩就好❄️/odd/割手手/碎碎念/喜欢你就会关注你/查成分互fo/性别女/不擅长交流T T比较社恐\n好鬼鬼喵https://t.co/DQnTNqAvfE",
        "entities": {
          "description": {
            "urls": [
              {
                "display_url": "x.com/Q7q7qqq",
                "end": 89,
                "expanded_url": "https://x.com/Q7q7qqq",
                "start": 66,
                "url": "https://t.co/DQnTNqAvfE"
              }
            ]
          },
          "url": {
            "urls": [
              {
                "display_url": "ngl.link/miami28394",
                "end": 23,
                "expanded_url": "https://ngl.link/miami28394",
                "start": 0,
                "url": "https://t.co/0v4C9Sd2n3"
              }
            ]
          }
        },
        "id": "1608743804034756609",
        "name": "眠",
        "pinned_tweet_id": "2032929294612095306",
        "profile_image_url": "https://pbs.twimg.com/profile_images/2034576519729692672/SyZ2pJTG_normal.jpg",
        "protected": false,
        "public_metrics": {
          "followers_count": 225,
          "following_count": 214,
          "like_count": 938,
          "listed_count": 0,
          "media_count": 17,
          "tweet_count": 800
        },
        "url": "https://t.co/0v4C9Sd2n3",
        "username": "catcatnekoyayay",
        "verified": false
      }
    ]
  }
}