{
  "data": {
    "article": {},
    "attachments": {},
    "author_id": "1598557374046179328",
    "conversation_id": "2072270412982198423",
    "created_at": "2026-07-06T16:26:57.000Z",
    "edit_controls": {
      "editable_until": "2026-07-06T17:26:57.000Z",
      "edits_remaining": 5,
      "is_edit_eligible": false
    },
    "edit_history_tweet_ids": [
      "2074168232253218965"
    ],
    "entities": {
      "mentions": [
        {
          "end": 16,
          "id": "1429478884722974724",
          "start": 0,
          "username": "fNT1cYSUkpu3myF"
        }
      ]
    },
    "geo": {},
    "id": "2074168232253218965",
    "in_reply_to_user_id": "1429478884722974724",
    "lang": "zh",
    "note_tweet": {
      "entities": {}
    },
    "possibly_sensitive": false,
    "public_metrics": {
      "bookmark_count": 0,
      "impression_count": 0,
      "like_count": 0,
      "quote_count": 0,
      "reply_count": 0,
      "retweet_count": 0
    },
    "referenced_tweets": [
      {
        "id": "2074162342187892843",
        "type": "replied_to"
      }
    ],
    "reply_settings": "everyone",
    "text": "@fNT1cYSUkpu3myF 我在枫湾"
  },
  "includes": {
    "tweets": [
      {
        "article": {},
        "attachments": {},
        "author_id": "1598557374046179328",
        "conversation_id": "2072270412982198423",
        "created_at": "2026-07-06T16:26:57.000Z",
        "edit_controls": {
          "editable_until": "2026-07-06T17:26:57.000Z",
          "edits_remaining": 5,
          "is_edit_eligible": false
        },
        "edit_history_tweet_ids": [
          "2074168232253218965"
        ],
        "entities": {
          "mentions": [
            {
              "end": 16,
              "id": "1429478884722974724",
              "start": 0,
              "username": "fNT1cYSUkpu3myF"
            }
          ]
        },
        "geo": {},
        "id": "2074168232253218965",
        "in_reply_to_user_id": "1429478884722974724",
        "lang": "zh",
        "note_tweet": {
          "entities": {}
        },
        "possibly_sensitive": false,
        "public_metrics": {
          "bookmark_count": 0,
          "impression_count": 0,
          "like_count": 0,
          "quote_count": 0,
          "reply_count": 0,
          "retweet_count": 0
        },
        "referenced_tweets": [
          {
            "id": "2074162342187892843",
            "type": "replied_to"
          }
        ],
        "reply_settings": "everyone",
        "text": "@fNT1cYSUkpu3myF 我在枫湾"
      },
      {
        "article": {},
        "attachments": {},
        "author_id": "1429478884722974724",
        "conversation_id": "2072270412982198423",
        "created_at": "2026-07-06T16:03:33.000Z",
        "edit_controls": {
          "editable_until": "2026-07-06T17:03:33.000Z",
          "edits_remaining": 5,
          "is_edit_eligible": false
        },
        "edit_history_tweet_ids": [
          "2074162342187892843"
        ],
        "entities": {
          "mentions": [
            {
              "end": 14,
              "id": "1598557374046179328",
              "start": 0,
              "username": "huihui_mikumi"
            }
          ]
        },
        "geo": {},
        "id": "2074162342187892843",
        "in_reply_to_user_id": "1598557374046179328",
        "lang": "ja",
        "note_tweet": {
          "entities": {}
        },
        "possibly_sensitive": false,
        "public_metrics": {
          "bookmark_count": 0,
          "impression_count": 4,
          "like_count": 0,
          "quote_count": 0,
          "reply_count": 1,
          "retweet_count": 0
        },
        "referenced_tweets": [
          {
            "id": "2074161720927621153",
            "type": "replied_to"
          }
        ],
        "reply_settings": "everyone",
        "text": "@huihui_mikumi 武江区"
      }
    ],
    "users": [
      {
        "created_at": "2022-12-02T05:59:21.000Z",
        "description": "|21|心理委员|依存症|mtf|xyn|二次元|特别粘人|不可以欺负我|特别害羞|杂鱼|腹黑|病娇|缺爱|抖M/S|自残|重抑|同类互fo\n\n 姐姐@Air_Yukiha 妹妹@nagis1a 小贱狗 @yuerQwQ",
        "entities": {
          "description": {
            "mentions": [
              {
                "end": 86,
                "start": 75,
                "username": "Air_Yukiha"
              },
              {
                "end": 97,
                "start": 89,
                "username": "nagis1a"
              },
              {
                "end": 110,
                "start": 102,
                "username": "yuerQwQ"
              }
            ]
          }
        },
        "id": "1598557374046179328",
        "location": "广东韶关",
        "name": "惠惠🍥🏳️‍⚧️（糖商）",
        "profile_image_url": "https://pbs.twimg.com/profile_images/2038850222680633345/r8zG5Gc1_normal.jpg",
        "protected": false,
        "public_metrics": {
          "followers_count": 2011,
          "following_count": 1052,
          "like_count": 938,
          "listed_count": 1,
          "media_count": 204,
          "tweet_count": 2291
        },
        "url": "",
        "username": "huihui_mikumi",
        "verified": true
      },
      {
        "created_at": "2021-08-22T16:21:54.000Z",
        "description": "广州、韶关",
        "id": "1429478884722974724",
        "name": "飙风",
        "profile_image_url": "https://pbs.twimg.com/profile_images/1500340909715693569/3JJinfvg_normal.jpg",
        "protected": false,
        "public_metrics": {
          "followers_count": 97,
          "following_count": 1316,
          "like_count": 840,
          "listed_count": 2,
          "media_count": 1,
          "tweet_count": 13
        },
        "url": "",
        "username": "fNT1cYSUkpu3myF",
        "verified": false
      }
    ]
  }
}