{
  "data": {
    "article": {},
    "attachments": {},
    "author_id": "1598557374046179328",
    "conversation_id": "2062107979898655116",
    "created_at": "2026-06-03T09:48:47.000Z",
    "edit_controls": {
      "editable_until": "2026-06-03T10:48:47.000Z",
      "edits_remaining": 5,
      "is_edit_eligible": false
    },
    "edit_history_tweet_ids": [
      "2062109233148227691"
    ],
    "entities": {
      "mentions": [
        {
          "end": 13,
          "id": "2027280531097088000",
          "start": 0,
          "username": "Lvmaosamaovo"
        }
      ]
    },
    "geo": {},
    "id": "2062109233148227691",
    "in_reply_to_user_id": "2027280531097088000",
    "lang": "zh",
    "note_tweet": {
      "entities": {}
    },
    "possibly_sensitive": false,
    "public_metrics": {
      "bookmark_count": 0,
      "impression_count": 0,
      "like_count": 0,
      "quote_count": 0,
      "reply_count": 0,
      "retweet_count": 0
    },
    "referenced_tweets": [
      {
        "id": "2062107979898655116",
        "type": "replied_to"
      }
    ],
    "reply_settings": "everyone",
    "text": "@Lvmaosamaovo 你还好嘛"
  },
  "includes": {
    "tweets": [
      {
        "article": {},
        "attachments": {},
        "author_id": "1598557374046179328",
        "conversation_id": "2062107979898655116",
        "created_at": "2026-06-03T09:48:47.000Z",
        "edit_controls": {
          "editable_until": "2026-06-03T10:48:47.000Z",
          "edits_remaining": 5,
          "is_edit_eligible": false
        },
        "edit_history_tweet_ids": [
          "2062109233148227691"
        ],
        "entities": {
          "mentions": [
            {
              "end": 13,
              "id": "2027280531097088000",
              "start": 0,
              "username": "Lvmaosamaovo"
            }
          ]
        },
        "geo": {},
        "id": "2062109233148227691",
        "in_reply_to_user_id": "2027280531097088000",
        "lang": "zh",
        "note_tweet": {
          "entities": {}
        },
        "possibly_sensitive": false,
        "public_metrics": {
          "bookmark_count": 0,
          "impression_count": 0,
          "like_count": 0,
          "quote_count": 0,
          "reply_count": 0,
          "retweet_count": 0
        },
        "referenced_tweets": [
          {
            "id": "2062107979898655116",
            "type": "replied_to"
          }
        ],
        "reply_settings": "everyone",
        "text": "@Lvmaosamaovo 你还好嘛"
      },
      {
        "article": {},
        "attachments": {},
        "author_id": "2027280531097088000",
        "conversation_id": "2062107979898655116",
        "created_at": "2026-06-03T09:43:49.000Z",
        "edit_controls": {
          "editable_until": "2026-06-03T10:43:49.000Z",
          "edits_remaining": 5,
          "is_edit_eligible": true
        },
        "edit_history_tweet_ids": [
          "2062107979898655116"
        ],
        "entities": {},
        "geo": {},
        "id": "2062107979898655116",
        "lang": "zh",
        "note_tweet": {
          "entities": {}
        },
        "possibly_sensitive": false,
        "public_metrics": {
          "bookmark_count": 0,
          "impression_count": 7,
          "like_count": 1,
          "quote_count": 0,
          "reply_count": 2,
          "retweet_count": 0
        },
        "reply_settings": "everyone",
        "text": "炸柜 无限期退出互联网 晚安"
      }
    ],
    "users": [
      {
        "created_at": "2022-12-02T05:59:21.000Z",
        "derived": {
          "locations": [
            {
              "country_code": "CN",
              "full_name": "Zhuhai, Guangdong Province, China",
              "geo": {
                "coordinates": [
                  113.56778,
                  22.27694
                ],
                "type": "Point"
              },
              "locality": "Zhuhai",
              "region": "Guangdong Province"
            }
          ]
        },
        "description": "|21|心理委员|依存症|mtf|xyn|二次元|特别粘人|不可以欺负我|特别害羞|杂鱼|腹黑|病娇|缺爱|抖M/S|自残|重抑|同类互fo",
        "id": "1598557374046179328",
        "location": "广州海珠",
        "name": "惠惠🍥🏳️‍⚧️（中二病也要mtf）",
        "profile_image_url": "https://pbs.twimg.com/profile_images/2038850222680633345/r8zG5Gc1_normal.jpg",
        "protected": false,
        "public_metrics": {
          "followers_count": 1124,
          "following_count": 614,
          "like_count": 634,
          "listed_count": 1,
          "media_count": 153,
          "tweet_count": 1424
        },
        "username": "huihui_mikumi",
        "verified": false
      },
      {
        "created_at": "2026-02-27T07:14:07.000Z",
        "description": "咕咕嘎嘎(๑˃̵ᴗ˂̵) 2011/10/27崭新出厂（mtf ｜主人@UnkMtX\n欢迎同类互fo 所有同类都会回fo喵～ hrt🍥｜2026_4_19 小号@Lvmaosamaqwq\n✝︎天使様、ご挨拶申し上げます！✝︎\n✝︎私は天より降り注ぐ光、混沌のネット世界を照らす存在なのです✝︎",
        "entities": {
          "description": {
            "mentions": [
              {
                "end": 42,
                "start": 35,
                "username": "UnkMtX"
              },
              {
                "end": 93,
                "start": 80,
                "username": "Lvmaosamaqwq"
              }
            ]
          }
        },
        "id": "2027280531097088000",
        "location": "上海精神卫生中心",
        "name": "☁️Lvmao๑˃̵ᴗ˂̵🍥〜",
        "profile_image_url": "https://pbs.twimg.com/profile_images/2046302106936897536/wD1z616h_normal.jpg",
        "protected": false,
        "public_metrics": {
          "followers_count": 732,
          "following_count": 335,
          "like_count": 2424,
          "listed_count": 1,
          "media_count": 58,
          "tweet_count": 735
        },
        "username": "Lvmaosamaovo",
        "verified": true
      }
    ]
  }
}