{
  "data": {
    "article": {},
    "attachments": {},
    "author_id": "1598557374046179328",
    "conversation_id": "2054902561782862320",
    "created_at": "2026-05-14T14:34:44.000Z",
    "edit_controls": {
      "editable_until": "2026-05-14T15:34:44.000Z",
      "edits_remaining": 5,
      "is_edit_eligible": false
    },
    "edit_history_tweet_ids": [
      "2054933436914352212"
    ],
    "entities": {
      "mentions": [
        {
          "end": 12,
          "id": "1942218528100134912",
          "start": 0,
          "username": "youling_qaq"
        },
        {
          "end": 18,
          "id": "1720665183188922368",
          "start": 13,
          "username": "grok"
        }
      ]
    },
    "geo": {},
    "id": "2054933436914352212",
    "in_reply_to_user_id": "1942218528100134912",
    "lang": "zh",
    "note_tweet": {
      "entities": {}
    },
    "possibly_sensitive": false,
    "public_metrics": {
      "bookmark_count": 0,
      "impression_count": 0,
      "like_count": 0,
      "quote_count": 0,
      "reply_count": 0,
      "retweet_count": 0
    },
    "referenced_tweets": [
      {
        "id": "2054902561782862320",
        "type": "replied_to"
      }
    ],
    "reply_settings": "everyone",
    "text": "@youling_qaq @grok 这是什么？"
  },
  "includes": {
    "media": [
      {
        "height": 2048,
        "media_key": "3_2054902559018778624",
        "public_metrics": {},
        "type": "photo",
        "url": "https://pbs.twimg.com/media/HIR6_XZbAAAlzf-.jpg",
        "width": 921
      }
    ],
    "tweets": [
      {
        "article": {},
        "attachments": {},
        "author_id": "1598557374046179328",
        "conversation_id": "2054902561782862320",
        "created_at": "2026-05-14T14:34:44.000Z",
        "edit_controls": {
          "editable_until": "2026-05-14T15:34:44.000Z",
          "edits_remaining": 5,
          "is_edit_eligible": false
        },
        "edit_history_tweet_ids": [
          "2054933436914352212"
        ],
        "entities": {
          "mentions": [
            {
              "end": 12,
              "id": "1942218528100134912",
              "start": 0,
              "username": "youling_qaq"
            },
            {
              "end": 18,
              "id": "1720665183188922368",
              "start": 13,
              "username": "grok"
            }
          ]
        },
        "geo": {},
        "id": "2054933436914352212",
        "in_reply_to_user_id": "1942218528100134912",
        "lang": "zh",
        "note_tweet": {
          "entities": {}
        },
        "possibly_sensitive": false,
        "public_metrics": {
          "bookmark_count": 0,
          "impression_count": 0,
          "like_count": 0,
          "quote_count": 0,
          "reply_count": 0,
          "retweet_count": 0
        },
        "referenced_tweets": [
          {
            "id": "2054902561782862320",
            "type": "replied_to"
          }
        ],
        "reply_settings": "everyone",
        "text": "@youling_qaq @grok 这是什么？"
      },
      {
        "article": {},
        "attachments": {
          "media_keys": [
            "3_2054902559018778624"
          ]
        },
        "author_id": "1942218528100134912",
        "conversation_id": "2054902561782862320",
        "created_at": "2026-05-14T12:32:03.000Z",
        "edit_controls": {
          "editable_until": "2026-05-14T13:32:03.000Z",
          "edits_remaining": 5,
          "is_edit_eligible": true
        },
        "edit_history_tweet_ids": [
          "2054902561782862320"
        ],
        "entities": {
          "urls": [
            {
              "display_url": "pic.x.com/B8iEtueHc7",
              "end": 31,
              "expanded_url": "https://x.com/youling_qaq/status/2054902561782862320/photo/1",
              "media_key": "3_2054902559018778624",
              "start": 8,
              "url": "https://t.co/B8iEtueHc7"
            }
          ]
        },
        "geo": {},
        "id": "2054902561782862320",
        "lang": "zh",
        "note_tweet": {
          "entities": {}
        },
        "possibly_sensitive": false,
        "public_metrics": {
          "bookmark_count": 0,
          "impression_count": 158,
          "like_count": 6,
          "quote_count": 0,
          "reply_count": 3,
          "retweet_count": 0
        },
        "reply_settings": "everyone",
        "text": "流动红旗已到账 https://t.co/B8iEtueHc7"
      }
    ],
    "users": [
      {
        "created_at": "2022-12-02T05:59:21.000Z",
        "derived": {
          "locations": [
            {
              "country_code": "CN",
              "full_name": "Zhuhai, Guangdong Province, China",
              "geo": {
                "coordinates": [
                  113.56778,
                  22.27694
                ],
                "type": "Point"
              },
              "locality": "Zhuhai",
              "region": "Guangdong Province"
            }
          ]
        },
        "description": "|21|心理委员|依存症|mtf|xyn|二次元|特别粘人|不可以欺负我|特别害羞|杂鱼|腹黑|病娇|缺爱|抖M/S|自残|重抑|互fo",
        "id": "1598557374046179328",
        "location": "广州海珠",
        "name": "惠惠🍥🏳️‍⚧️（中二病也要mtf）",
        "pinned_tweet_id": "2039216871254401419",
        "profile_image_url": "https://pbs.twimg.com/profile_images/2038850222680633345/r8zG5Gc1_normal.jpg",
        "protected": false,
        "public_metrics": {
          "followers_count": 897,
          "following_count": 483,
          "like_count": 489,
          "listed_count": 1,
          "media_count": 123,
          "tweet_count": 1005
        },
        "username": "huihui_mikumi",
        "verified": false
      },
      {
        "created_at": "2025-07-07T13:46:08.000Z",
        "description": "求求了，被 ghost ban 了，不是不发帖，别取关啊😭😭😭\n\n12 年 mtf oder oier\n\n坐标 hncs\n\n蓝勾是为了 grok\n\n可以叫我幽零",
        "entities": {
          "url": {
            "urls": [
              {
                "display_url": "basibatuo.fun",
                "end": 23,
                "expanded_url": "http://basibatuo.fun/",
                "start": 0,
                "url": "https://t.co/VCWcmoh4Lm"
              }
            ]
          }
        },
        "id": "1942218528100134912",
        "name": "basibatuo",
        "profile_image_url": "https://pbs.twimg.com/profile_images/2022914453998891008/mwmzVtyR_normal.jpg",
        "protected": false,
        "public_metrics": {
          "followers_count": 702,
          "following_count": 906,
          "like_count": 2170,
          "listed_count": 2,
          "media_count": 39,
          "tweet_count": 555
        },
        "url": "https://t.co/VCWcmoh4Lm",
        "username": "youling_qaq",
        "verified": true
      },
      {
        "created_at": "2023-11-04T04:52:34.000Z",
        "description": "@grok it",
        "entities": {
          "description": {
            "mentions": [
              {
                "end": 5,
                "start": 0,
                "username": "grok"
              }
            ]
          },
          "url": {
            "urls": [
              {
                "display_url": "grok.com/download",
                "end": 23,
                "expanded_url": "http://grok.com/download",
                "start": 0,
                "url": "https://t.co/fqNKQSjjG9"
              }
            ]
          }
        },
        "id": "1720665183188922368",
        "name": "Grok",
        "profile_image_url": "https://pbs.twimg.com/profile_images/2052556247870865408/oGdJ7sXt_normal.jpg",
        "protected": false,
        "public_metrics": {
          "followers_count": 8736926,
          "following_count": 4,
          "like_count": 93,
          "listed_count": 6832,
          "media_count": 8928525,
          "tweet_count": 125773591
        },
        "url": "https://t.co/fqNKQSjjG9",
        "username": "grok",
        "verified": true
      }
    ]
  }
}