{
  "data": {
    "article": {},
    "attachments": {
      "media_keys": [
        "3_2042447271506460672",
        "3_2042447274538872832"
      ]
    },
    "author_id": "1598557374046179328",
    "conversation_id": "2042113958933622845",
    "created_at": "2026-04-10T03:39:12.000Z",
    "edit_controls": {
      "editable_until": "2026-04-10T04:39:12.000Z",
      "edits_remaining": 5,
      "is_edit_eligible": false
    },
    "edit_history_tweet_ids": [
      "2042447277986652567"
    ],
    "entities": {
      "mentions": [
        {
          "end": 14,
          "id": "1611246341728120835",
          "start": 0,
          "username": "Aureliax17QwQ"
        }
      ],
      "urls": [
        {
          "display_url": "pic.x.com/jl104yfk6n",
          "end": 38,
          "expanded_url": "https://x.com/huihui_mikumi/status/2042447277986652567/photo/1",
          "media_key": "3_2042447271506460672",
          "start": 15,
          "url": "https://t.co/jl104yfk6n"
        },
        {
          "display_url": "pic.x.com/jl104yfk6n",
          "end": 38,
          "expanded_url": "https://x.com/huihui_mikumi/status/2042447277986652567/photo/1",
          "media_key": "3_2042447274538872832",
          "start": 15,
          "url": "https://t.co/jl104yfk6n"
        }
      ]
    },
    "geo": {},
    "id": "2042447277986652567",
    "in_reply_to_user_id": "1611246341728120835",
    "lang": "qme",
    "note_tweet": {
      "entities": {}
    },
    "possibly_sensitive": false,
    "public_metrics": {
      "bookmark_count": 0,
      "impression_count": 0,
      "like_count": 0,
      "quote_count": 0,
      "reply_count": 0,
      "retweet_count": 0
    },
    "referenced_tweets": [
      {
        "id": "2042447062726582479",
        "type": "replied_to"
      }
    ],
    "reply_settings": "everyone",
    "text": "@Aureliax17QwQ https://t.co/jl104yfk6n"
  },
  "includes": {
    "media": [
      {
        "height": 1200,
        "media_key": "3_2042447271506460672",
        "public_metrics": {},
        "type": "photo",
        "url": "https://pbs.twimg.com/media/HFg6-NqbwAAR4Cc.jpg",
        "width": 1200
      },
      {
        "height": 1819,
        "media_key": "3_2042447274538872832",
        "public_metrics": {},
        "type": "photo",
        "url": "https://pbs.twimg.com/media/HFg6-Y9asAAVlw-.jpg",
        "width": 1204
      }
    ],
    "tweets": [
      {
        "article": {},
        "attachments": {
          "media_keys": [
            "3_2042447271506460672",
            "3_2042447274538872832"
          ]
        },
        "author_id": "1598557374046179328",
        "conversation_id": "2042113958933622845",
        "created_at": "2026-04-10T03:39:12.000Z",
        "edit_controls": {
          "editable_until": "2026-04-10T04:39:12.000Z",
          "edits_remaining": 5,
          "is_edit_eligible": false
        },
        "edit_history_tweet_ids": [
          "2042447277986652567"
        ],
        "entities": {
          "mentions": [
            {
              "end": 14,
              "id": "1611246341728120835",
              "start": 0,
              "username": "Aureliax17QwQ"
            }
          ],
          "urls": [
            {
              "display_url": "pic.x.com/jl104yfk6n",
              "end": 38,
              "expanded_url": "https://x.com/huihui_mikumi/status/2042447277986652567/photo/1",
              "media_key": "3_2042447271506460672",
              "start": 15,
              "url": "https://t.co/jl104yfk6n"
            },
            {
              "display_url": "pic.x.com/jl104yfk6n",
              "end": 38,
              "expanded_url": "https://x.com/huihui_mikumi/status/2042447277986652567/photo/1",
              "media_key": "3_2042447274538872832",
              "start": 15,
              "url": "https://t.co/jl104yfk6n"
            }
          ]
        },
        "geo": {},
        "id": "2042447277986652567",
        "in_reply_to_user_id": "1611246341728120835",
        "lang": "qme",
        "note_tweet": {
          "entities": {}
        },
        "possibly_sensitive": false,
        "public_metrics": {
          "bookmark_count": 0,
          "impression_count": 0,
          "like_count": 0,
          "quote_count": 0,
          "reply_count": 0,
          "retweet_count": 0
        },
        "referenced_tweets": [
          {
            "id": "2042447062726582479",
            "type": "replied_to"
          }
        ],
        "reply_settings": "everyone",
        "text": "@Aureliax17QwQ https://t.co/jl104yfk6n"
      },
      {
        "article": {},
        "attachments": {},
        "author_id": "1611246341728120835",
        "conversation_id": "2042113958933622845",
        "created_at": "2026-04-10T03:38:21.000Z",
        "edit_controls": {
          "editable_until": "2026-04-10T04:38:21.000Z",
          "edits_remaining": 5,
          "is_edit_eligible": false
        },
        "edit_history_tweet_ids": [
          "2042447062726582479"
        ],
        "entities": {
          "mentions": [
            {
              "end": 14,
              "id": "1598557374046179328",
              "start": 0,
              "username": "huihui_mikumi"
            }
          ]
        },
        "geo": {},
        "id": "2042447062726582479",
        "in_reply_to_user_id": "1598557374046179328",
        "lang": "zh",
        "note_tweet": {
          "entities": {}
        },
        "possibly_sensitive": false,
        "public_metrics": {
          "bookmark_count": 0,
          "impression_count": 1,
          "like_count": 0,
          "quote_count": 0,
          "reply_count": 1,
          "retweet_count": 0
        },
        "referenced_tweets": [
          {
            "id": "2042445704212463776",
            "type": "replied_to"
          }
        ],
        "reply_settings": "everyone",
        "text": "@huihui_mikumi 不要买😭"
      }
    ],
    "users": [
      {
        "created_at": "2022-12-02T05:59:21.000Z",
        "description": "|21|心理委员|依存症|mtf|xyn|二次元|特别粘人|不可以欺负我|特别害羞|杂鱼|腹黑|病娇|OD药|缺爱|抖M/S|自残|欢迎互fo\n\n在替某人活下去，帮助更多想结束生命之人",
        "id": "1598557374046179328",
        "location": "广州",
        "name": "惠惠🍥🏳️‍⚧️（中二病也要mtf）",
        "pinned_tweet_id": "2039216871254401419",
        "profile_image_url": "https://pbs.twimg.com/profile_images/2038850222680633345/r8zG5Gc1_normal.jpg",
        "protected": false,
        "public_metrics": {
          "followers_count": 405,
          "following_count": 278,
          "like_count": 229,
          "listed_count": 0,
          "media_count": 74,
          "tweet_count": 440
        },
        "username": "huihui_mikumi",
        "verified": false
      },
      {
        "created_at": "2023-01-06T06:20:59.000Z",
        "description": "神经病兼免费但失败的心理委员，可以把我当树洞｜mtf｜06｜重抑｜INFP｜已炸柜｜💊｜想倾诉或聊天可以tg找我说话（或者私信哦～）|tg：https://t.co/5kLEQoTlFF |最爱的小孩@dnshu135734｜永远爱你们❤️",
        "entities": {
          "description": {
            "mentions": [
              {
                "end": 112,
                "start": 100,
                "username": "dnshu135734"
              }
            ],
            "urls": [
              {
                "display_url": "t.me/Aureliax17",
                "end": 93,
                "expanded_url": "http://t.me/Aureliax17",
                "start": 70,
                "url": "https://t.co/5kLEQoTlFF"
              }
            ]
          },
          "url": {
            "urls": [
              {
                "display_url": "ngl.link/aureliax17",
                "end": 23,
                "expanded_url": "https://ngl.link/aureliax17",
                "start": 0,
                "url": "https://t.co/h6OCEkrSu6"
              }
            ]
          }
        },
        "id": "1611246341728120835",
        "location": "长安",
        "name": "海月水母x17🍥",
        "profile_image_url": "https://pbs.twimg.com/profile_images/2008776444445626368/iHOJfO5R_normal.jpg",
        "protected": false,
        "public_metrics": {
          "followers_count": 1578,
          "following_count": 348,
          "like_count": 6119,
          "listed_count": 2,
          "media_count": 130,
          "tweet_count": 1625
        },
        "url": "https://t.co/h6OCEkrSu6",
        "username": "Aureliax17QwQ",
        "verified": true
      }
    ]
  }
}